<?xml version="1.0" encoding="UTF-8"?>
<objects serializationModel="Studio.02.02.00">
	<object class="AudioFile" id="{7de3860f-1269-40a7-b3c4-89f45c0faa49}">
		<property name="assetPath">
			<value>Designed, Rumble, Crackle, Warble, Mid, Rocks, Sci Fi SND111783 6.wav</value>
		</property>
		<property name="frequencyInKHz">
			<value>48</value>
		</property>
		<property name="channelCount">
			<value>2</value>
		</property>
		<property name="length">
			<value>0.43422916666666667</value>
		</property>
		<relationship name="masterAssetFolder">
			<destination>{9f4425e6-7a76-4fba-978c-8fd1a48a6662}</destination>
		</relationship>
	</object>
</objects>
